delvewheel/__init__.py
delvewheel/__main__.py
delvewheel/_dll_list.py
delvewheel/_dll_utils.py
delvewheel/_version.py
delvewheel/_wheel_repair.py
delvewheel-1.12.0.dist-info/licenses/LICENSE
delvewheel-1.12.0.dist-info/METADATA
delvewheel-1.12.0.dist-info/WHEEL
delvewheel-1.12.0.dist-info/entry_points.txt
delvewheel-1.12.0.dist-info/top_level.txt
delvewheel-1.12.0.dist-info/RECORD
