Metadata-Version: 2.4
Name: delvewheel
Version: 1.12.0
Summary: Self-contained wheels for Windows
Author-email: Aohan Dang <adang1345@gmail.com>
License-Expression: MIT
Project-URL: Homepage, https://github.com/adang1345/delvewheel
Project-URL: Documentation, https://github.com/adang1345/delvewheel/blob/master/README.md
Project-URL: Changelog, https://github.com/adang1345/delvewheel/blob/master/CHANGELOG.md
Platform: Windows
Classifier: Programming Language :: Python :: 3
Classifier: Programming Language :: Python :: 3 :: Only
Classifier: Programming Language :: Python :: 3.9
Classifier: Programming Language :: Python :: 3.10
Classifier: Programming Language :: Python :: 3.11
Classifier: Programming Language :: Python :: 3.12
Classifier: Programming Language :: Python :: 3.13
Classifier: Programming Language :: Python :: 3.14
Classifier: Environment :: Console
Classifier: Development Status :: 5 - Production/Stable
Classifier: Operating System :: Microsoft :: Windows
Classifier: Topic :: Software Development
Classifier: Topic :: Software Development :: Build Tools
Classifier: Topic :: Software Development :: Libraries :: Python Modules
Requires-Python: >=3.9
License-File: LICENSE
Requires-Dist: pefile>=2024.8.26
Dynamic: license-file
